src/__init__.py
src/kafkajobs/__init__.py
src/kafkajobs/jobqueue/__init__.py
src/kafkajobs/jobqueue/queue.py
src/kafkajobs/serialization/__init__.py
src/kafkajobs/serialization/image.py
src/kafkajobs/serialization/np.py
kafka_job_scheduler-1.0.0.dist-info/METADATA
kafka_job_scheduler-1.0.0.dist-info/WHEEL
kafka_job_scheduler-1.0.0.dist-info/license_files/LICENSE
kafka_job_scheduler-1.0.0.dist-info/RECORD
