Metadata-Version: 2.1
Name: kafka-job-scheduler
Version: 1.0.0
Summary: A job queue based on Apache Kafka
Project-URL: Homepage, https://github.com/LostPetInitiative/kafka-job-scheduler
Project-URL: Bug Tracker, https://github.com/LostPetInitiative/kafka-job-scheduler
Author-email: Dmitry Grechka <dmitry@kashtanka.pet>
License: MIT License
Classifier: License :: OSI Approved :: MIT License
Classifier: Operating System :: OS Independent
Classifier: Programming Language :: Python :: 3
Requires-Python: >=3.7
